stepfun_mcp/client.py
stepfun_mcp/const.py
stepfun_mcp/exceptions.py
stepfun_mcp/server.py
stepfun_mcp/utils.py
stepfun_mcp-0.0.2.dist-info/METADATA
stepfun_mcp-0.0.2.dist-info/WHEEL
stepfun_mcp-0.0.2.dist-info/entry_points.txt
stepfun_mcp-0.0.2.dist-info/top_level.txt
stepfun_mcp-0.0.2.dist-info/RECORD
