Metadata-Version: 2.4
Name: stepfun-mcp
Version: 0.0.2
Summary: StepFun MCP Server
Author-email: Tristan <weidafeng.edu@gmail.com>
Keywords: stepfun,mcp,text-generation,vision,image-generation,speech
Classifier: Development Status :: 3 - Alpha
Classifier: Intended Audience :: Developers
Classifier: Programming Language :: Python :: 3
Classifier: Programming Language :: Python :: 3.11
Classifier: Programming Language :: Python :: 3.12
Requires-Python: >=3.11
Requires-Dist: mcp[cli]>=1.6.0
Requires-Dist: fastapi>=0.109.2
Requires-Dist: uvicorn>=0.27.1
Requires-Dist: python-dotenv>=1.0.1
Requires-Dist: pydantic>=2.6.1
Requires-Dist: requests>=2.31.0
Requires-Dist: fastmcp>=0.1.0
Requires-Dist: Pillow>=10.0.0
Requires-Dist: python-Levenshtein
Requires-Dist: fuzzywuzzy
Requires-Dist: openai
Provides-Extra: dev
Requires-Dist: pre-commit; extra == "dev"
Requires-Dist: ruff; extra == "dev"
Requires-Dist: pytest; extra == "dev"
Requires-Dist: pytest-cov; extra == "dev"
